dspydantic/__init__.py
dspydantic/extractor.py
dspydantic/module.py
dspydantic/optimizer.py
dspydantic/persistence.py
dspydantic/prompter.py
dspydantic/types.py
dspydantic/utils.py
dspydantic/evaluators/__init__.py
dspydantic/evaluators/config.py
dspydantic/evaluators/functions.py
dspydantic/evaluators/label_model_grader.py
dspydantic/evaluators/levenshtein.py
dspydantic/evaluators/predefined_score.py
dspydantic/evaluators/python_code.py
dspydantic/evaluators/score_judge.py
dspydantic/evaluators/string_check.py
dspydantic/evaluators/text_similarity.py
dspydantic-0.1.1.dist-info/METADATA
dspydantic-0.1.1.dist-info/WHEEL
dspydantic-0.1.1.dist-info/licenses/LICENSE
dspydantic-0.1.1.dist-info/RECORD
