Metadata-Version: 2.4
Name: dspydantic
Version: 0.1.1
Summary: Optimize Pydantic model field descriptions using DSPy
Author: dspydantic contributors
License: MIT
License-File: LICENSE
Keywords: ai,dspy,llm,optimization,pydantic
Classifier: Development Status :: 3 - Alpha
Classifier: Intended Audience :: Developers
Classifier: License :: OSI Approved :: MIT License
Classifier: Programming Language :: Python :: 3
Classifier: Programming Language :: Python :: 3.11
Classifier: Programming Language :: Python :: 3.12
Classifier: Topic :: Software Development :: Libraries :: Python Modules
Requires-Python: >=3.11
Requires-Dist: deepdiff>=8.0.0
Requires-Dist: dspy>=3.0.4
Requires-Dist: pdf2image>=1.16.0
Requires-Dist: pillow>=10.0.0
Requires-Dist: pydantic>=2.0.0
Provides-Extra: dev
Requires-Dist: black>=24.0.0; extra == 'dev'
Requires-Dist: datasets; extra == 'dev'
Requires-Dist: mypy>=1.8.0; extra == 'dev'
Requires-Dist: pre-commit>=3.6.0; extra == 'dev'
Requires-Dist: pytest>=8.4.2; extra == 'dev'
Requires-Dist: ruff>=0.1.0; extra == 'dev'
Requires-Dist: watchdog>=4.0.0; extra == 'dev'
Provides-Extra: docs
Requires-Dist: jupyter>=1.0.0; extra == 'docs'
Requires-Dist: mkdocs-jupyter>=0.24.0; extra == 'docs'
Requires-Dist: mkdocs-material>=9.5.0; extra == 'docs'
Requires-Dist: mkdocstrings[python]>=0.24.0; extra == 'docs'
Requires-Dist: mktestdocs>=0.1.0; extra == 'docs'
Requires-Dist: nbconvert>=7.0.0; extra == 'docs'
